LICENSE
sqlalchemy_events.py
sqlalchemy_events-0.1.0.dist-info/LICENSE
sqlalchemy_events-0.1.0.dist-info/WHEEL
sqlalchemy_events-0.1.0.dist-info/METADATA
sqlalchemy_events-0.1.0.dist-info/RECORD
